sqs_launcher/__init__.py
sqs_listener/__init__.py
sqs_listener/daemon.py
pyAsyncSqsListener-0.10.0.dist-info/LICENSE
pyAsyncSqsListener-0.10.0.dist-info/METADATA
pyAsyncSqsListener-0.10.0.dist-info/WHEEL
pyAsyncSqsListener-0.10.0.dist-info/top_level.txt
pyAsyncSqsListener-0.10.0.dist-info/RECORD
