Metadata-Version: 2.1
Name: pyAsyncSqsListener
Version: 0.10.0
Summary: A simple Python SQS utility package
Home-page: https://github.com/rathourarv/async-sqs-listener
Author: Arvind Singh
Author-email: rathourarv@gmail.com
License: Apache Software License
Keywords: aws sqs listener and message launcher
Classifier: Development Status :: 4 - Beta
Classifier: Intended Audience :: Developers
Classifier: Topic :: Software Development :: Libraries
Classifier: License :: OSI Approved :: Apache Software License
Classifier: Programming Language :: Python :: 3.11
License-File: LICENSE
Requires-Dist: boto3
Provides-Extra: dev
Requires-Dist: black ; extra == 'dev'
